sent_sim_embedding/__init__.py
sent_sim_embedding/rocketqa/__init__.py
sent_sim_embedding/rocketqa/rocketqa.py
sent_sim_embedding/tests/__init__.py
sent_sim_embedding-1.0.0.1.dist-info/METADATA
sent_sim_embedding-1.0.0.1.dist-info/WHEEL
sent_sim_embedding-1.0.0.1.dist-info/top_level.txt
sent_sim_embedding-1.0.0.1.dist-info/RECORD
