Metadata-Version: 2.1
Name: sent-sim-embedding
Version: 1.0.0.1
Summary: 文本语义向量和相关性计算
Home-page: https://codeup.aliyun.com/64650c96168f0a5963451dec/lib/sent-sim-embedding/blob/master/README.md
Author: yes_bobo
Author-email: fb_linux@163.com
License: MIT
Platform: UNKNOWN
Classifier: Programming Language :: Python
Classifier: Programming Language :: Python :: 3
Classifier: Programming Language :: Python :: 3.8
Requires-Dist: rocketqa (==1.1.0)
Requires-Dist: pydantic
Requires-Dist: numpy
